geo_mcp_server/__init__.py
geo_mcp_server-0.5.0.dist-info/licenses/LICENSE
geo_mcp_server-0.5.0.dist-info/METADATA
geo_mcp_server-0.5.0.dist-info/WHEEL
geo_mcp_server-0.5.0.dist-info/top_level.txt
geo_mcp_server-0.5.0.dist-info/RECORD
