Metadata-Version: 2.4
Name: geo-mcp-server
Version: 0.5.0
Summary: DEPRECATED: This package is no longer maintained. Use https://github.com/MCPmed/GEOmcp instead.
Home-page: https://github.com/MCPmed/GEOmcp
Author: MCP Developer
Author-email: developer@example.com
Keywords: deprecated,bioinformatics,e-utils,gene-expression,geo,mcp,ncbi,geneexpression,mcp-server
Classifier: Development Status :: 7 - Inactive
Classifier: Intended Audience :: Science/Research
Classifier: License :: OSI Approved :: MIT License
Classifier: Operating System :: OS Independent
Classifier: Programming Language :: Python :: 3
Classifier: Programming Language :: Python :: 3.8
Classifier: Programming Language :: Python :: 3.9
Classifier: Programming Language :: Python :: 3.10
Classifier: Programming Language :: Python :: 3.11
Classifier: Topic :: Scientific/Engineering :: Bio-Informatics
Requires-Python: >=3.8
License-File: LICENSE
Dynamic: author
Dynamic: author-email
Dynamic: classifier
Dynamic: description
Dynamic: description-content-type
Dynamic: home-page
Dynamic: keywords
Dynamic: license-file
Dynamic: requires-python
Dynamic: summary
